ess/bifrost/__init__.py
ess/bifrost/cutting.py
ess/bifrost/data.py
ess/bifrost/detector.py
ess/bifrost/live.py
ess/bifrost/normalization.py
ess/bifrost/py.typed
ess/bifrost/types.py
ess/bifrost/workflow.py
ess/bifrost/io/__init__.py
ess/bifrost/io/mcstas.py
ess/bifrost/io/nexus.py
ess/bifrost/io/sqw.py
ess/bifrost/single_crystal/__init__.py
ess/bifrost/single_crystal/conversion.py
ess/bifrost/single_crystal/q_map.py
ess/bifrost/single_crystal/time_of_flight.py
ess/bifrost/single_crystal/types.py
ess/bifrost/single_crystal/workflow.py
ess/spectroscopy/__init__.py
ess/spectroscopy/py.typed
ess/spectroscopy/types.py
ess/spectroscopy/indirect/__init__.py
ess/spectroscopy/indirect/conversion.py
ess/spectroscopy/indirect/io.py
ess/spectroscopy/indirect/kf.py
ess/spectroscopy/indirect/ki.py
ess/spectroscopy/indirect/time_of_flight.py
essspectroscopy-26.1.0.dist-info/licenses/LICENSE
essspectroscopy-26.1.0.dist-info/METADATA
essspectroscopy-26.1.0.dist-info/WHEEL
essspectroscopy-26.1.0.dist-info/top_level.txt
essspectroscopy-26.1.0.dist-info/RECORD
