Metadata-Version: 2.4
Name: essspectroscopy
Version: 26.1.0
Summary: Spectroscopy data reduction for the European Spallation Source 
Author: Scipp contributors
License-Expression: BSD-3-Clause
Project-URL: Bug Tracker, https://github.com/scipp/essspectroscopy/issues
Project-URL: Documentation, https://scipp.github.io/essspectroscopy
Project-URL: Source, https://github.com/scipp/essspectroscopy
Classifier: Intended Audience :: Science/Research
Classifier: Natural Language :: English
Classifier: Operating System :: OS Independent
Classifier: Programming Language :: Python :: 3
Classifier: Programming Language :: Python :: 3 :: Only
Classifier: Programming Language :: Python :: 3.11
Classifier: Programming Language :: Python :: 3.12
Classifier: Programming Language :: Python :: 3.13
Classifier: Topic :: Scientific/Engineering
Classifier: Typing :: Typed
Requires-Python: >=3.11
License-File: LICENSE
Requires-Dist: essreduce>=25.11.3
Requires-Dist: graphviz>=0.20
Requires-Dist: pandas>=2.1.2
Requires-Dist: sciline>=25.4.1
Requires-Dist: scipp>=25.3.0
Requires-Dist: scippneutron>=25.11.2
Requires-Dist: scippnexus>=24.9.0
Requires-Dist: tof>=25.11.0
Provides-Extra: test
Requires-Dist: pooch>=1.5; extra == "test"
Requires-Dist: pytest>=7.0; extra == "test"
Dynamic: license-file
